{
  "produto": [
    {
      "id": "1",
      "nome": "vestido Florido",
      "preco": 100.9,
      "imagem": "vestido_florido.jpg",
      "colecaoId": "2",
      "tamanho": "M",
      "quantidade_estoque": 8,
      "quantidade_vendida": 6
    },
    {
      "id": "2",
      "nome": "Macacão com estampa preta",
      "preco": 200,
      "imagem": "macacão_branco_flores_pretas.jpg",
      "colecaoId": "2",
      "tamanho": "G",
      "quantidade_estoque": 4,
      "quantidade_vendida": 3
    },
    {
      "id": "3",
      "nome": "Camisa Caroá",
      "preco": 90,
      "imagem": "camisa_caroá.png",
      "colecaoId": "1",
      "tamanho": "P",
      "quantidade_estoque": 8,
      "quantidade_vendida": 3
    },
    {
      "id": "4",
      "nome": "Camisa Estampada Branca",
      "preco": 80,
      "imagem": "camisa-branca-com-detalhes.jpg",
      "colecaoId": "2",
      "tamanho": "M",
      "quantidade_estoque": 12,
      "quantidade_vendida": 0
    },
    {
      "id": "5",
      "nome": "bermuda estampada",
      "preco": 50,
      "imagem": "camisa_caroá.png",
      "colecaoId": "1",
      "tamanho": "G",
      "quantidade_estoque": 15,
      "quantidade_vendida": 0
    },
    {
      "id": "6",
      "nome": "Camisa Estampada Bege",
      "preco": 79,
      "imagem": "camisa-estampada.png",
      "colecaoId": "2",
      "tamanho": "G",
      "quantidade_estoque": 15,
      "quantidade_vendida": 0
    },
    {
      "id": "7",
      "nome": "Vestido estampado laranja",
      "preco": 250,
      "imagem": "vestido_folhas_laranjas.png",
      "colecaoId": "2",
      "tamanho": "G",
      "quantidade_estoque": 15,
      "quantidade_vendida": 0
    },
    {
      "id": "8",
      "nome": "Saia estampada azul",
      "preco": 120,
      "imagem": "saia_azul.jpg",
      "colecaoId": "2",
      "tamanho": "M",
      "quantidade_estoque": 15,
      "quantidade_vendida": 0
    },
    {
      "id": "9",
      "nome": "Vestido estampado verde",
      "preco": 150,
      "imagem": "vestido_folhas_verdes.png",
      "colecaoId": "1",
      "tamanho": "G",
      "quantidade_estoque": 15,
      "quantidade_vendida": 0
    },
    {
      "id": "10",
      "nome": "Saia estampada vermelha",
      "preco": 130,
      "imagem": "saia_vermelha.jpg",
      "colecaoId": "2",
      "tamanho": "M",
      "quantidade_estoque": 15,
      "quantidade_vendida": 0
    }
  ],
  "colecao": [
    {
      "id": "1",
      "nome": "Coleção Caroá",
      "descricao": "Inspirada na tradição e cultura da família Serafim, a Coleção Caroá traz gravuras exclusivas e estampas autorais que celebram a conexão entre gerações. Cada peça é pensada para unir conforto, beleza e história, tornando-se um elo entre a nossa família e a sua.",
      "imagem": "test1.jpg"
    },
    {
      "id": "2",
      "nome": "Coleção Nordestina",
      "descricao": "A Coleção Nordestina homenageia as cores, texturas e a alegria do Nordeste brasileiro. Com estampas vibrantes e detalhes únicos, cada peça traduz a energia, a criatividade e o calor humano típicos da nossa região, levando um pouco do Nordeste para o seu dia a dia.",
      "imagem": "nordestina.jpg"
    }
  ],
  "pedido": [
    {
      "id": "1",
      "status": "Concluído",
      "valor_total": 0,
      "produtos": [
        {
          "produtoId": "5",
          "quantidade": 1
        }
      ]
    },
    {
      "id": "2",
      "status": "Concluído",
      "valor_total": 0,
      "produtos": [
        {
          "produtoId": "2",
          "quantidade": 1
        }
      ]
    },
    {
      "id": "3",
      "status": "Concluído",
      "valor_total": 280.9,
      "produtos": [
        {
          "produtoId": "3",
          "quantidade": 2
        },
        {
          "produtoId": "1",
          "quantidade": 1
        }
      ]
    },
    {
      "id": "4",
      "status": "Concluído",
      "valor_total": 90,
      "produtos": [
        {
          "produtoId": "3",
          "quantidade": 1
        }
      ]
    },
    {
      "id": "5",
      "status": "Concluído",
      "valor_total": 378.9,
      "produtos": [
        {
          "produtoId": "1",
          "quantidade": 1
        },
        {
          "produtoId": "6",
          "quantidade": 2
        },
        {
          "produtoId": "8",
          "quantidade": 1
        }
      ]
    },
    {
      "id": "6",
      "status": "Concluído",
      "valor_total": 90,
      "produtos": [
        {
          "produtoId": "3",
          "quantidade": 1
        }
      ]
    },
    {
      "id": "7",
      "status": "Concluído",
      "valor_total": 380,
      "produtos": [
        {
          "produtoId": "2",
          "quantidade": 1
        },
        {
          "produtoId": "3",
          "quantidade": 2
        }
      ]
    },
    {
      "id": "8",
      "status": "Concluído",
      "valor_total": 302.70000000000005,
      "produtos": [
        {
          "produtoId": "1",
          "quantidade": 3
        }
      ]
    },
    {
      "id": "9",
      "status": "Concluído",
      "valor_total": 302.70000000000005,
      "produtos": [
        {
          "produtoId": "1",
          "quantidade": 3
        }
      ]
    },
    {
      "id": "10",
      "status": "Concluído",
      "valor_total": 200,
      "produtos": [
        {
          "produtoId": "2",
          "quantidade": 1
        }
      ]
    },
    {
      "id": "11",
      "status": "Pendente",
      "valor_total": 0,
      "produtos": [
        {
          "produtoId": "1",
          "quantidade": 1
        }
      ]
    }
  ]
}